{
    "os": "Linux-5.4.0-144-generic-x86_64-with-glibc2.35",
    "python": "3.9.17",
    "heartbeatAt": "2023-09-04T21:25:51.593084",
    "startedAt": "2023-09-04T21:25:51.409159",
    "docker": null,
    "cuda": null,
    "args": [
        "minimal_size=128",
        "length=16",
        "use_wandb=false"
    ],
    "state": "running",
    "program": "/root/BitFlip/DQNwithHer/main.py",
    "codePath": "DQNwithHer/main.py",
    "git": {
        "remote": "git@github.com:chjchjchjchjchj/BitFlip.git",
        "commit": "3e94036f08916c2a5ef16e56dc8fe4bfd70a1396"
    },
    "email": "chjchjchjchjchj2001@gmail.com",
    "root": "/root/BitFlip",
    "host": "autodl-container-30b911be3c-f093d3ff",
    "username": "root",
    "executable": "/root/miniconda3/envs/ling/bin/python",
    "cpu_count": 64,
    "cpu_count_logical": 128,
    "cpu_freq": {
        "current": 1055.9839296875,
        "min": 800.0,
        "max": 3500.0
    },
    "cpu_freq_per_core": [
        {
            "current": 899.116,
            "min": 800.0,
            "max": 3500.0
        },
        {
            "current": 2303.539,
            "min": 800.0,
            "max": 3500.0
        },
        {
            "current": 791.58,
            "min": 800.0,
            "max": 3500.0
        },
        {
            "current": 1637.333,
            "min": 800.0,
            "max": 3500.0
        },
        {
            "current": 800.208,
            "min": 800.0,
            "max": 3500.0
        },
        {
            "current": 800.913,
            "min": 800.0,
            "max": 3500.0
        },
        {
            "current": 1185.016,
            "min": 800.0,
            "max": 3500.0
        },
        {
            "current": 801.819,
            "min": 800.0,
            "max": 3500.0
        },
        {
            "current": 855.516,
            "min": 800.0,
            "max": 3500.0
        },
        {
            "current": 855.014,
            "min": 800.0,
            "max": 3500.0
        },
        {
            "current": 823.549,
            "min": 800.0,
            "max": 3500.0
        },
        {
            "current": 893.503,
            "min": 800.0,
            "max": 3500.0
        },
        {
            "current": 800.262,
            "min": 800.0,
            "max": 3500.0
        },
        {
            "current": 863.345,
            "min": 800.0,
            "max": 3500.0
        },
        {
            "current": 800.26,
            "min": 800.0,
            "max": 3500.0
        },
        {
            "current": 800.89,
            "min": 800.0,
            "max": 3500.0
        },
        {
            "current": 800.884,
            "min": 800.0,
            "max": 3500.0
        },
        {
            "current": 800.867,
            "min": 800.0,
            "max": 3500.0
        },
        {
            "current": 826.485,
            "min": 800.0,
            "max": 3500.0
        },
        {
            "current": 801.32,
            "min": 800.0,
            "max": 3500.0
        },
        {
            "current": 800.121,
            "min": 800.0,
            "max": 3500.0
        },
        {
            "current": 982.873,
            "min": 800.0,
            "max": 3500.0
        },
        {
            "current": 800.446,
            "min": 800.0,
            "max": 3500.0
        },
        {
            "current": 854.78,
            "min": 800.0,
            "max": 3500.0
        },
        {
            "current": 1032.311,
            "min": 800.0,
            "max": 3500.0
        },
        {
            "current": 801.337,
            "min": 800.0,
            "max": 3500.0
        },
        {
            "current": 793.446,
            "min": 800.0,
            "max": 3500.0
        },
        {
            "current": 800.438,
            "min": 800.0,
            "max": 3500.0
        },
        {
            "current": 801.005,
            "min": 800.0,
            "max": 3500.0
        },
        {
            "current": 2432.224,
            "min": 800.0,
            "max": 3500.0
        },
        {
            "current": 793.567,
            "min": 800.0,
            "max": 3500.0
        },
        {
            "current": 899.127,
            "min": 800.0,
            "max": 3500.0
        },
        {
            "current": 2579.799,
            "min": 800.0,
            "max": 3500.0
        },
        {
            "current": 834.098,
            "min": 800.0,
            "max": 3500.0
        },
        {
            "current": 2406.58,
            "min": 800.0,
            "max": 3500.0
        },
        {
            "current": 800.883,
            "min": 800.0,
            "max": 3500.0
        },
        {
            "current": 915.666,
            "min": 800.0,
            "max": 3500.0
        },
        {
            "current": 997.461,
            "min": 800.0,
            "max": 3500.0
        },
        {
            "current": 801.287,
            "min": 800.0,
            "max": 3500.0
        },
        {
            "current": 800.853,
            "min": 800.0,
            "max": 3500.0
        },
        {
            "current": 801.334,
            "min": 800.0,
            "max": 3500.0
        },
        {
            "current": 2602.918,
            "min": 800.0,
            "max": 3500.0
        },
        {
            "current": 1216.029,
            "min": 800.0,
            "max": 3500.0
        },
        {
            "current": 801.253,
            "min": 800.0,
            "max": 3500.0
        },
        {
            "current": 1470.278,
            "min": 800.0,
            "max": 3500.0
        },
        {
            "current": 800.839,
            "min": 800.0,
            "max": 3500.0
        },
        {
            "current": 801.288,
            "min": 800.0,
            "max": 3500.0
        },
        {
            "current": 2600.0,
            "min": 800.0,
            "max": 3500.0
        },
        {
            "current": 800.868,
            "min": 800.0,
            "max": 3500.0
        },
        {
            "current": 800.871,
            "min": 800.0,
            "max": 3500.0
        },
        {
            "current": 800.385,
            "min": 800.0,
            "max": 3500.0
        },
        {
            "current": 800.425,
            "min": 800.0,
            "max": 3500.0
        },
        {
            "current": 800.348,
            "min": 800.0,
            "max": 3500.0
        },
        {
            "current": 800.312,
            "min": 800.0,
            "max": 3500.0
        },
        {
            "current": 2448.592,
            "min": 800.0,
            "max": 3500.0
        },
        {
            "current": 800.866,
            "min": 800.0,
            "max": 3500.0
        },
        {
            "current": 800.875,
            "min": 800.0,
            "max": 3500.0
        },
        {
            "current": 786.093,
            "min": 800.0,
            "max": 3500.0
        },
        {
            "current": 973.937,
            "min": 800.0,
            "max": 3500.0
        },
        {
            "current": 800.445,
            "min": 800.0,
            "max": 3500.0
        },
        {
            "current": 801.325,
            "min": 800.0,
            "max": 3500.0
        },
        {
            "current": 800.873,
            "min": 800.0,
            "max": 3500.0
        },
        {
            "current": 801.723,
            "min": 800.0,
            "max": 3500.0
        },
        {
            "current": 801.295,
            "min": 800.0,
            "max": 3500.0
        },
        {
            "current": 896.387,
            "min": 800.0,
            "max": 3500.0
        },
        {
            "current": 1884.699,
            "min": 800.0,
            "max": 3500.0
        },
        {
            "current": 800.896,
            "min": 800.0,
            "max": 3500.0
        },
        {
            "current": 1359.336,
            "min": 800.0,
            "max": 3500.0
        },
        {
            "current": 800.457,
            "min": 800.0,
            "max": 3500.0
        },
        {
            "current": 788.073,
            "min": 800.0,
            "max": 3500.0
        },
        {
            "current": 800.899,
            "min": 800.0,
            "max": 3500.0
        },
        {
            "current": 800.22,
            "min": 800.0,
            "max": 3500.0
        },
        {
            "current": 823.904,
            "min": 800.0,
            "max": 3500.0
        },
        {
            "current": 827.366,
            "min": 800.0,
            "max": 3500.0
        },
        {
            "current": 862.973,
            "min": 800.0,
            "max": 3500.0
        },
        {
            "current": 786.244,
            "min": 800.0,
            "max": 3500.0
        },
        {
            "current": 801.393,
            "min": 800.0,
            "max": 3500.0
        },
        {
            "current": 801.378,
            "min": 800.0,
            "max": 3500.0
        },
        {
            "current": 876.963,
            "min": 800.0,
            "max": 3500.0
        },
        {
            "current": 902.185,
            "min": 800.0,
            "max": 3500.0
        },
        {
            "current": 836.749,
            "min": 800.0,
            "max": 3500.0
        },
        {
            "current": 1025.026,
            "min": 800.0,
            "max": 3500.0
        },
        {
            "current": 859.542,
            "min": 800.0,
            "max": 3500.0
        },
        {
            "current": 890.529,
            "min": 800.0,
            "max": 3500.0
        },
        {
            "current": 827.772,
            "min": 800.0,
            "max": 3500.0
        },
        {
            "current": 911.669,
            "min": 800.0,
            "max": 3500.0
        },
        {
            "current": 1045.801,
            "min": 800.0,
            "max": 3500.0
        },
        {
            "current": 857.028,
            "min": 800.0,
            "max": 3500.0
        },
        {
            "current": 1242.337,
            "min": 800.0,
            "max": 3500.0
        },
        {
            "current": 878.284,
            "min": 800.0,
            "max": 3500.0
        },
        {
            "current": 856.238,
            "min": 800.0,
            "max": 3500.0
        },
        {
            "current": 1294.689,
            "min": 800.0,
            "max": 3500.0
        },
        {
            "current": 922.711,
            "min": 800.0,
            "max": 3500.0
        },
        {
            "current": 2591.953,
            "min": 800.0,
            "max": 3500.0
        },
        {
            "current": 1402.428,
            "min": 800.0,
            "max": 3500.0
        },
        {
            "current": 825.904,
            "min": 800.0,
            "max": 3500.0
        },
        {
            "current": 2603.245,
            "min": 800.0,
            "max": 3500.0
        },
        {
            "current": 891.506,
            "min": 800.0,
            "max": 3500.0
        },
        {
            "current": 2594.969,
            "min": 800.0,
            "max": 3500.0
        },
        {
            "current": 838.839,
            "min": 800.0,
            "max": 3500.0
        },
        {
            "current": 800.877,
            "min": 800.0,
            "max": 3500.0
        },
        {
            "current": 800.907,
            "min": 800.0,
            "max": 3500.0
        },
        {
            "current": 800.897,
            "min": 800.0,
            "max": 3500.0
        },
        {
            "current": 800.433,
            "min": 800.0,
            "max": 3500.0
        },
        {
            "current": 1481.572,
            "min": 800.0,
            "max": 3500.0
        },
        {
            "current": 2599.998,
            "min": 800.0,
            "max": 3500.0
        },
        {
            "current": 2600.001,
            "min": 800.0,
            "max": 3500.0
        },
        {
            "current": 834.461,
            "min": 800.0,
            "max": 3500.0
        },
        {
            "current": 800.89,
            "min": 800.0,
            "max": 3500.0
        },
        {
            "current": 854.346,
            "min": 800.0,
            "max": 3500.0
        },
        {
            "current": 800.44,
            "min": 800.0,
            "max": 3500.0
        },
        {
            "current": 2600.0,
            "min": 800.0,
            "max": 3500.0
        },
        {
            "current": 1064.266,
            "min": 800.0,
            "max": 3500.0
        },
        {
            "current": 856.956,
            "min": 800.0,
            "max": 3500.0
        },
        {
            "current": 800.435,
            "min": 800.0,
            "max": 3500.0
        },
        {
            "current": 875.602,
            "min": 800.0,
            "max": 3500.0
        },
        {
            "current": 800.456,
            "min": 800.0,
            "max": 3500.0
        },
        {
            "current": 801.336,
            "min": 800.0,
            "max": 3500.0
        },
        {
            "current": 2595.715,
            "min": 800.0,
            "max": 3500.0
        },
        {
            "current": 801.355,
            "min": 800.0,
            "max": 3500.0
        },
        {
            "current": 1069.34,
            "min": 800.0,
            "max": 3500.0
        },
        {
            "current": 818.918,
            "min": 800.0,
            "max": 3500.0
        },
        {
            "current": 878.126,
            "min": 800.0,
            "max": 3500.0
        },
        {
            "current": 1521.377,
            "min": 800.0,
            "max": 3500.0
        },
        {
            "current": 801.357,
            "min": 800.0,
            "max": 3500.0
        },
        {
            "current": 801.344,
            "min": 800.0,
            "max": 3500.0
        },
        {
            "current": 800.904,
            "min": 800.0,
            "max": 3500.0
        },
        {
            "current": 800.436,
            "min": 800.0,
            "max": 3500.0
        }
    ],
    "disk": {
        "total": 30.0,
        "used": 10.866291046142578
    },
    "gpu": "NVIDIA GeForce RTX 3090",
    "gpu_count": 1,
    "gpu_devices": [
        {
            "name": "NVIDIA GeForce RTX 3090",
            "memory_total": 25769803776
        }
    ],
    "memory": {
        "total": 503.538028717041
    }
}
